DaShujufenxiJishuYuYingyongYizhanshiXuexiCYuyanBianchengWang/README.md
DaShujufenxiJishuYuYingyongYizhanshiXuexiCYuyanBianchengWang/__init__.py
DaShujufenxiJishuYuYingyongYizhanshiXuexiCYuyanBianchengWang/__main__.py
DaShujufenxiJishuYuYingyongYizhanshiXuexiCYuyanBianchengWang/file.epub
DaShujufenxiJishuYuYingyongYizhanshiXuexiCYuyanBianchengWang/index.html
DaShujufenxiJishuYuYingyongYizhanshiXuexiCYuyanBianchengWang/css/__init__.py
DaShujufenxiJishuYuYingyongYizhanshiXuexiCYuyanBianchengWang/css/annotations.css
DaShujufenxiJishuYuYingyongYizhanshiXuexiCYuyanBianchengWang/css/main.css
DaShujufenxiJishuYuYingyongYizhanshiXuexiCYuyanBianchengWang/css/normalize.css
DaShujufenxiJishuYuYingyongYizhanshiXuexiCYuyanBianchengWang/css/popup.css
DaShujufenxiJishuYuYingyongYizhanshiXuexiCYuyanBianchengWang/font/__init__.py
DaShujufenxiJishuYuYingyongYizhanshiXuexiCYuyanBianchengWang/font/fontello.eot
DaShujufenxiJishuYuYingyongYizhanshiXuexiCYuyanBianchengWang/font/fontello.svg
DaShujufenxiJishuYuYingyongYizhanshiXuexiCYuyanBianchengWang/font/fontello.ttf
DaShujufenxiJishuYuYingyongYizhanshiXuexiCYuyanBianchengWang/font/fontello.woff
DaShujufenxiJishuYuYingyongYizhanshiXuexiCYuyanBianchengWang/img/__init__.py
DaShujufenxiJishuYuYingyongYizhanshiXuexiCYuyanBianchengWang/img/annotator-glyph-sprite.png
DaShujufenxiJishuYuYingyongYizhanshiXuexiCYuyanBianchengWang/img/annotator-icon-sprite.png
DaShujufenxiJishuYuYingyongYizhanshiXuexiCYuyanBianchengWang/img/apple-touch-icon.png
DaShujufenxiJishuYuYingyongYizhanshiXuexiCYuyanBianchengWang/img/cancelfullscreen.png
DaShujufenxiJishuYuYingyongYizhanshiXuexiCYuyanBianchengWang/img/close.png
DaShujufenxiJishuYuYingyongYizhanshiXuexiCYuyanBianchengWang/img/fullscreen.png
DaShujufenxiJishuYuYingyongYizhanshiXuexiCYuyanBianchengWang/img/loader.gif
DaShujufenxiJishuYuYingyongYizhanshiXuexiCYuyanBianchengWang/img/menu-icon.png
DaShujufenxiJishuYuYingyongYizhanshiXuexiCYuyanBianchengWang/img/save.png
da_shujufenxi_jishu_yu_yingyong_yizhanshi_xuexi_c_yuyan_biancheng_wang-2024.3.5.0.dist-info/METADATA
da_shujufenxi_jishu_yu_yingyong_yizhanshi_xuexi_c_yuyan_biancheng_wang-2024.3.5.0.dist-info/WHEEL
da_shujufenxi_jishu_yu_yingyong_yizhanshi_xuexi_c_yuyan_biancheng_wang-2024.3.5.0.dist-info/entry_points.txt
da_shujufenxi_jishu_yu_yingyong_yizhanshi_xuexi_c_yuyan_biancheng_wang-2024.3.5.0.dist-info/top_level.txt
da_shujufenxi_jishu_yu_yingyong_yizhanshi_xuexi_c_yuyan_biancheng_wang-2024.3.5.0.dist-info/RECORD
